yelpfusion/__init__.py
yelpfusion/endpoint.py
yelpfusion/endpoints/__init__.py
yelpfusion/endpoints/autocomplete.py
yelpfusion/endpoints/businesses.py
yelpfusion/endpoints/categories.py
yelpfusion/endpoints/events.py
yelpfusion/endpoints/transactions.py
yelpfusion/py.typed
yelpfusion/yelp_fusion.py
yelpfusion-0.1.1.dist-info/LICENSE
yelpfusion-0.1.1.dist-info/WHEEL
yelpfusion-0.1.1.dist-info/METADATA
yelpfusion-0.1.1.dist-info/RECORD
